Metadata-Version: 2.1
Name: compynieshouse
Version: 0.0.4
Summary: A convenient wrapper for the UK Companies House REST API
Home-page: https://github.com/HEtothe/compynieshouse
Author: HEtothe
License: MIT
Platform: UNKNOWN
Classifier: License :: OSI Approved :: MIT License
Classifier: Programming Language :: Python :: 3
Classifier: Programming Language :: Python :: 3.6
